arp_standard_client/__init__.py
arp_standard_client/errors.py
arp_standard_client/py.typed
arp_standard_client/atomic_executor/__init__.py
arp_standard_client/atomic_executor/client.py
arp_standard_client/atomic_executor/errors.py
arp_standard_client/atomic_executor/facade.py
arp_standard_client/atomic_executor/types.py
arp_standard_client/atomic_executor/api/__init__.py
arp_standard_client/atomic_executor/api/atomic_node_runs/__init__.py
arp_standard_client/atomic_executor/api/atomic_node_runs/cancel_atomic_node_run.py
arp_standard_client/atomic_executor/api/atomic_node_runs/execute_atomic_node_run.py
arp_standard_client/atomic_executor/api/health/__init__.py
arp_standard_client/atomic_executor/api/health/health.py
arp_standard_client/atomic_executor/api/version/__init__.py
arp_standard_client/atomic_executor/api/version/version.py
arp_standard_client/clients/__init__.py
arp_standard_client/clients/atomic_executor.py
arp_standard_client/clients/composite_executor.py
arp_standard_client/clients/node_registry.py
arp_standard_client/clients/pdp.py
arp_standard_client/clients/run_coordinator.py
arp_standard_client/clients/run_gateway.py
arp_standard_client/clients/selection.py
arp_standard_client/composite_executor/__init__.py
arp_standard_client/composite_executor/client.py
arp_standard_client/composite_executor/errors.py
arp_standard_client/composite_executor/facade.py
arp_standard_client/composite_executor/types.py
arp_standard_client/composite_executor/api/__init__.py
arp_standard_client/composite_executor/api/composite_node_runs/__init__.py
arp_standard_client/composite_executor/api/composite_node_runs/begin_composite_node_run.py
arp_standard_client/composite_executor/api/composite_node_runs/cancel_composite_node_run.py
arp_standard_client/composite_executor/api/health/__init__.py
arp_standard_client/composite_executor/api/health/health.py
arp_standard_client/composite_executor/api/version/__init__.py
arp_standard_client/composite_executor/api/version/version.py
arp_standard_client-0.3.7.dist-info/licenses/LICENSE
arp_standard_client-0.3.7.dist-info/METADATA
arp_standard_client-0.3.7.dist-info/WHEEL
arp_standard_client-0.3.7.dist-info/top_level.txt
arp_standard_client-0.3.7.dist-info/RECORD
