Metadata-Version: 2.4
Name: arp-standard-client
Version: 0.3.7
Summary: Python client package for the ARP Standard (v1).
Author: Agent Runtime Protocol
License-Expression: MIT
Project-URL: Repository, https://github.com/AgentRuntimeProtocol/ARP_Standard
Project-URL: Issues, https://github.com/AgentRuntimeProtocol/ARP_Standard/issues
Requires-Python: >=3.11
License-File: LICENSE
Requires-Dist: attrs>=22.2.0
Requires-Dist: httpx>=0.23.0
Requires-Dist: python-dateutil>=2.8.1
Requires-Dist: arp-standard-model==0.3.7
Provides-Extra: dev
Requires-Dist: pytest>=7; extra == "dev"
Requires-Dist: pyright>=1.1.0; extra == "dev"
Dynamic: license-file
